scribae/__init__.py
scribae/brief.py
scribae/brief_cli.py
scribae/idea.py
scribae/idea_cli.py
scribae/io_utils.py
scribae/language.py
scribae/llm.py
scribae/main.py
scribae/meta.py
scribae/meta_cli.py
scribae/project.py
scribae/snippets.py
scribae/translate_cli.py
scribae/version_cli.py
scribae/write.py
scribae/write_cli.py
scribae/prompts/__init__.py
scribae/prompts/brief.py
scribae/prompts/idea.py
scribae/prompts/meta.py
scribae/prompts/write.py
scribae/translate/__init__.py
scribae/translate/markdown_segmenter.py
scribae/translate/model_registry.py
scribae/translate/mt.py
scribae/translate/pipeline.py
scribae/translate/postedit.py
scribae-0.1.0.dist-info/licenses/LICENSE
scribae-0.1.0.dist-info/METADATA
scribae-0.1.0.dist-info/WHEEL
scribae-0.1.0.dist-info/entry_points.txt
scribae-0.1.0.dist-info/top_level.txt
scribae-0.1.0.dist-info/RECORD
