Metadata-Version: 2.4
Name: scribae
Version: 0.1.0
Summary: CLI that turns local Markdown notes into structured SEO content packages using LLMs while keeping the human in the loop.
Author-email: Felix Müller <felix@fmueller.io>
License-Expression: Apache-2.0
Project-URL: Homepage, https://github.com/fmueller/scribae
Project-URL: Repository, https://github.com/fmueller/scribae
Project-URL: Issues, https://github.com/fmueller/scribae/issues
Project-URL: Changelog, https://github.com/fmueller/scribae/blob/main/CHANGELOG.md
Keywords: cli,content,llm,markdown,nlp,seo,translation,writing
Classifier: Development Status :: 3 - Alpha
Classifier: Environment :: Console
Classifier: Intended Audience :: Developers
Classifier: Operating System :: OS Independent
Classifier: Programming Language :: Python :: 3
Classifier: Programming Language :: Python :: 3.10
Classifier: Programming Language :: Python :: 3.11
Classifier: Programming Language :: Python :: 3.12
Classifier: Topic :: Text Processing
Classifier: Topic :: Text Processing :: Linguistic
Requires-Python: >=3.10
License-File: LICENSE
Requires-Dist: pydantic>=2.12.4
Requires-Dist: pydantic-ai>=1.12.0
Requires-Dist: typer>=0.20.0
Requires-Dist: pyyaml>=6.0.2
Requires-Dist: python-frontmatter>=1.1.0
Requires-Dist: transformers>=4.46.3
Requires-Dist: sentencepiece>=0.2.0
Requires-Dist: sacremoses>=0.1.1
Requires-Dist: fast-langdetect>=1.0.0
Requires-Dist: fasttext-predict==0.9.2.4
Requires-Dist: tomli>=2.0.0; python_version < "3.11"
Provides-Extra: translation
Requires-Dist: torch>=2.5.1; extra == "translation"
Dynamic: license-file
